metadoc/__init__.py
metadoc/install.py
metadoc/domain/__init__.py
metadoc/domain/blacklists.py
metadoc/domain/check.py
metadoc/domain/domaintools.py
metadoc/domain/lookup.py
metadoc/extract/__init__.py
metadoc/extract/extractor.py
metadoc/extract/html.py
metadoc/extract/ner.py
metadoc/extract/pos.py
metadoc/extract/data/tagger.pickle
metadoc/extract/data/training_set.txt
metadoc/extract/data/chunkers/maxent_ne_chunker/english_ace_binary.pickle
metadoc/extract/data/chunkers/maxent_ne_chunker/english_ace_multiclass.pickle
metadoc/extract/data/chunkers/maxent_ne_chunker/PY3/english_ace_binary.pickle
metadoc/extract/data/chunkers/maxent_ne_chunker/PY3/english_ace_multiclass.pickle
metadoc/extract/data/corpora/brown/CONTENTS
metadoc/extract/data/corpora/brown/README
metadoc/extract/data/corpora/brown/ca01
metadoc/extract/data/corpora/brown/ca02
metadoc/extract/data/corpora/brown/ca03
metadoc/extract/data/corpora/brown/ca04
metadoc/extract/data/corpora/brown/ca05
metadoc/extract/data/corpora/brown/ca06
metadoc/extract/data/corpora/brown/ca07
metadoc/extract/data/corpora/brown/ca08
metadoc/extract/data/corpora/brown/ca09
metadoc/extract/data/corpora/brown/ca10
metadoc/extract/data/corpora/brown/ca11
metadoc/extract/data/corpora/brown/ca12
metadoc/extract/data/corpora/brown/ca13
metadoc/extract/data/corpora/brown/ca14
metadoc/extract/data/corpora/brown/ca15
metadoc/extract/data/corpora/brown/ca16
metadoc/extract/data/corpora/brown/ca17
metadoc/extract/data/corpora/brown/ca18
metadoc/extract/data/corpora/brown/ca19
metadoc/extract/data/corpora/brown/ca20
metadoc/extract/data/corpora/brown/ca21
metadoc/extract/data/corpora/brown/ca22
metadoc/extract/data/corpora/brown/ca23
metadoc/extract/data/corpora/brown/ca24
metadoc/extract/data/corpora/brown/ca25
metadoc/extract/data/corpora/brown/ca26
metadoc/extract/data/corpora/brown/ca27
metadoc/extract/data/corpora/brown/ca28
metadoc/extract/data/corpora/brown/ca29
metadoc-0.10.5.dist-info/METADATA
metadoc-0.10.5.dist-info/RECORD
metadoc-0.10.5.dist-info/WHEEL
metadoc-0.10.5.dist-info/top_level.txt
