Metadata-Version: 2.1
Name: metadoc
Version: 0.10.5
Summary: Post-truth era news article metadata service.
Home-page: https://github.com/praise-internet/metadoc
Author: Paul Solbach
Author-email: p@psolbach.com
License: MIT
Keywords: scraping,metadata,news article
Platform: UNKNOWN
Classifier: Programming Language :: Python :: 3.5
Classifier: Topic :: Internet :: WWW/HTTP
Classifier: Development Status :: 3 - Alpha
Classifier: License :: OSI Approved :: MIT License
Classifier: Intended Audience :: Developers
Classifier: Operating System :: POSIX :: Linux
Classifier: Environment :: Web Environment
Requires-Dist: aiohttp (==1.1.5)
Requires-Dist: bottle (==0.12.10)
Requires-Dist: python-dateutil (==2.6.1)
Requires-Dist: jmespath (==0.9.0)
Requires-Dist: langdetect (==1.0.7)
Requires-Dist: goose3 (==3.0.9)
Requires-Dist: nltk (==3.2.1)
Requires-Dist: numpy (==1.13.3)
Requires-Dist: requests (==2.18.4)
Requires-Dist: tldextract (==2.0.2)
Requires-Dist: whois (==0.7)
